MANIFEST.in
README.md
setup.cfg
setup.py
3rdparty/toulbar2-0.9.7.0/x86_64/Linux/toulbar2
3rdparty/toulbar2-0.9.7.0/x86_64/Windows/toulbar2.exe
_version/__init__.py
examples/alarm/alarm.pracmln
examples/hmm/hmm.pracmln
examples/meals/meals.pracmln
examples/object-recognition/object-recognition.pracmln
examples/smokers/smokers.pracmln
examples/taxonomies/taxonomies.pracmln
examples/tweety/tweety.pracmln
examples/vegetarians/vegetarians.pracmln
libpracmln/CMakeLists.txt
libpracmln/build/CMakeCache.txt
libpracmln/build/Makefile
libpracmln/build/cmake_install.cmake
libpracmln/build/install_manifest.txt
libpracmln/build/libpracmln.so
libpracmln/build/test_mln
libpracmln/build/CMakeFiles/CMakeDirectoryInformation.cmake
libpracmln/build/CMakeFiles/CMakeOutput.log
libpracmln/build/CMakeFiles/Makefile.cmake
libpracmln/build/CMakeFiles/Makefile2
libpracmln/build/CMakeFiles/TargetDirectories.txt
libpracmln/build/CMakeFiles/cmake.check_cache
libpracmln/build/CMakeFiles/feature_tests.bin
libpracmln/build/CMakeFiles/feature_tests.c
libpracmln/build/CMakeFiles/feature_tests.cxx
libpracmln/build/CMakeFiles/progress.marks
libpracmln/build/CMakeFiles/3.5.1/CMakeCCompiler.cmake
libpracmln/build/CMakeFiles/3.5.1/CMakeCXXCompiler.cmake
libpracmln/build/CMakeFiles/3.5.1/CMakeDetermineCompilerABI_C.bin
libpracmln/build/CMakeFiles/3.5.1/CMakeDetermineCompilerABI_CXX.bin
libpracmln/build/CMakeFiles/3.5.1/CMakeSystem.cmake
libpracmln/build/CMakeFiles/3.5.1/CompilerIdC/CMakeCCompilerId.c
libpracmln/build/CMakeFiles/3.5.1/CompilerIdC/a.out
libpracmln/build/CMakeFiles/3.5.1/CompilerIdCXX/CMakeCXXCompilerId.cpp
libpracmln/build/CMakeFiles/3.5.1/CompilerIdCXX/a.out
libpracmln/build/CMakeFiles/header_files.dir/DependInfo.cmake
libpracmln/build/CMakeFiles/header_files.dir/build.make
libpracmln/build/CMakeFiles/header_files.dir/cmake_clean.cmake
libpracmln/build/CMakeFiles/header_files.dir/progress.make
libpracmln/build/CMakeFiles/pracmln.dir/CXX.includecache
pracmln.egg-info/PKG-INFO
pracmln.egg-info/SOURCES.txt
pracmln.egg-info/dependency_links.txt
pracmln.egg-info/entry_points.txt
pracmln.egg-info/requires.txt
pracmln.egg-info/top_level.txt
