Metadata-Version: 1.1
Name: pracmln
Version: 1.2.0
Summary: A collection of convenience tools for everyday Python programming
Home-page: https://pracmln.org
Author: Daniel Nyga
Author-email: nyga@cs.uni-bremen.de
License: UNKNOWN
Download-URL: https://github.com/danielnyga/pracmln/archive/1.2.0.tar.gz
Keywords: statistical relational learning,mln,Markov logic networks,reasoning,probcog
Platform: UNKNOWN
Classifier: Development Status :: 4 - Beta
Classifier: Intended Audience :: Developers
Classifier: Topic :: Software Development :: Libraries :: Python Modules
Classifier: Topic :: Scientific/Engineering :: Artificial Intelligence 
Classifier: License :: OSI Approved :: MIT License
Classifier: Programming Language :: Python :: 2
Classifier: Programming Language :: Python :: 2.7
Classifier: Programming Language :: Python :: 3
Classifier: Programming Language :: Python :: 3.5
